{
  "kind": "collectionType",
  "collectionName": "items",
  "info": {
    "name": "Item"
  },
  "options": {
    "increments": true,
    "timestamps": true
  },
  "attributes": {
    "Name": {
      "type": "string"
    },
    "Description": {
      "type": "text"
    },
    "Image": {
      "model": "file",
      "via": "related",
      "allowedTypes": [
        "images",
        "files",
        "videos"
      ],
      "plugin": "upload",
      "required": false
    },
    "Price": {
      "type": "float"
    },
    "Available": {
      "type": "boolean"
    },
    "meal": {
      "model": "meal",
      "via": "items"
    }
  }
}
